jganenokloh/zhizha.py
jganenokloh-1.0.0.dist-info/METADATA
jganenokloh-1.0.0.dist-info/WHEEL
jganenokloh-1.0.0.dist-info/top_level.txt
jganenokloh-1.0.0.dist-info/RECORD
