Metadata-Version: 2.4
Name: jganenokloh
Version: 1.0.0
Summary: jganenok лох
Author-email: noxzion <negroid2281488ilikrilex@gmail.com>
License: MIT
Keywords: mongodb,motor,pydantic,async,odm
Classifier: Programming Language :: Python :: 3
Classifier: License :: OSI Approved :: MIT License
Classifier: Operating System :: OS Independent
Requires-Python: >=3.7
Requires-Dist: motor>=2.5.1
Requires-Dist: pydantic>=1.10.2
